org_model_logs/__init__.py
org_model_logs/admin.py
org_model_logs/api.py
org_model_logs/apps.py
org_model_logs/migrations/0001_initial.py
org_model_logs/migrations/0002_alter_communicationslogentry_options.py
org_model_logs/migrations/0003_alter_useraction_unique_together.py
org_model_logs/migrations/0004_alter_communicationslogentry_unique_together.py
org_model_logs/migrations/0005_useraction_why.py
org_model_logs/migrations/0006_auto_20220902_1357.py
org_model_logs/migrations/0007_alter_entrytype_options.py
org_model_logs/migrations/0008_rename_type_entrytype_entry_type.py
org_model_logs/migrations/0009_alter_communicationslogentry_customer.py
org_model_logs/migrations/0010_alter_communicationslogentry_options.py
org_model_logs/migrations/__init__.py
org_model_logs/models.py
org_model_logs/serializers.py
org_model_logs/tests.py
org_model_logs/urls.py
org_model_logs/utils.py
org_model_logs/views.py
django_org_model_logs-1.1.1.dist-info/LICENSE
django_org_model_logs-1.1.1.dist-info/WHEEL
django_org_model_logs-1.1.1.dist-info/METADATA
django_org_model_logs-1.1.1.dist-info/RECORD
